setup.py
cppmangle/__init__.py
cppmangle/__main__.py
cppmangle/ast.py
cppmangle/cdecl.py
cppmangle/mangle.py
cppmangle/msvc.py
cppmangle.egg-info/PKG-INFO
cppmangle.egg-info/SOURCES.txt
cppmangle.egg-info/dependency_links.txt
cppmangle.egg-info/entry_points.txt
cppmangle.egg-info/requires.txt
cppmangle.egg-info/top_level.txt