Metadata-Version: 1.0
Name: cppmangle
Version: 0.2
Summary: A parser for mangled C++ names
Home-page: https://github.com/AVGTechnologies/cppmangle
Author: AVG Technologies CZ, s.r.o.
Author-email: UNKNOWN
License: Apache 2.0
Platform: UNKNOWN
